wenvkernel/__init__.py
wenvkernel/_core.py
wenvkernel/_logos.py
wenvkernel/install.py
wenvkernel-0.0.1.dist-info/LICENSE
wenvkernel-0.0.1.dist-info/METADATA
wenvkernel-0.0.1.dist-info/WHEEL
wenvkernel-0.0.1.dist-info/top_level.txt
wenvkernel-0.0.1.dist-info/RECORD
