Metadata-Version: 2.1
Name: wenvkernel
Version: 0.0.1
Summary: Jupyter kernel for Python on Wine
Home-page: https://github.com/pleiszenburg/wenv-kernel
Author: Sebastian M. Ernst
Author-email: ernst@pleiszenburg.de
License: LGPLv2
Download-URL: https://github.com/pleiszenburg/wenv-kernel/archive/v0.0.1.tar.gz
Keywords: wine,cross platform,jupyter,notebook,kernel
Platform: UNKNOWN
Classifier: Development Status :: 4 - Beta
Classifier: Intended Audience :: Developers
Classifier: Intended Audience :: Information Technology
Classifier: Intended Audience :: Science/Research
Classifier: License :: OSI Approved :: GNU Lesser General Public License v2 (LGPLv2)
Classifier: Operating System :: MacOS
Classifier: Operating System :: POSIX :: BSD
Classifier: Operating System :: POSIX :: Linux
Classifier: Programming Language :: Python :: 3
Classifier: Programming Language :: Python :: 3.4
Classifier: Programming Language :: Python :: 3.5
Classifier: Programming Language :: Python :: 3.6
Classifier: Programming Language :: Python :: 3.7
Classifier: Programming Language :: Python :: 3.8
Classifier: Programming Language :: Python :: 3 :: Only
Classifier: Programming Language :: Python :: Implementation :: CPython
Classifier: Topic :: Scientific/Engineering
Classifier: Topic :: Software Development
Classifier: Topic :: System :: Operating System
Classifier: Topic :: System :: Operating System Kernels
Classifier: Topic :: Utilities
Requires-Python: >=3.4
Requires-Dist: jupyterlab
Requires-Dist: wenv (~=0.2.0)
Provides-Extra: dev
Requires-Dist: black ; extra == 'dev'
Requires-Dist: pytest ; extra == 'dev'
Requires-Dist: coverage ; extra == 'dev'
Requires-Dist: pytest-cov ; extra == 'dev'
Requires-Dist: python-language-server ; extra == 'dev'
Requires-Dist: jupyter-kernel-test ; extra == 'dev'
Requires-Dist: setuptools ; extra == 'dev'
Requires-Dist: Sphinx ; extra == 'dev'
Requires-Dist: sphinx-rtd-theme ; extra == 'dev'
Requires-Dist: twine ; extra == 'dev'
Requires-Dist: wheel ; extra == 'dev'
